package_speech_recognizer/__init__.py
package_speech_recognizer-0.2.8.dist-info/METADATA
package_speech_recognizer-0.2.8.dist-info/WHEEL
package_speech_recognizer-0.2.8.dist-info/top_level.txt
package_speech_recognizer-0.2.8.dist-info/RECORD
