Metadata-Version: 2.1
Name: package-speech-recognizer
Version: 0.2.8
Summary: In this package you can find the easiest way to create a speech recogniser including background recognizing solution
Home-page: UNKNOWN
Author: Ankit Biswas
License: UNKNOWN
Platform: UNKNOWN
Requires-Dist: SpeechRecognition
Requires-Dist: pyttsx3
